gantry/__init__.py
gantry/evaluations.py
gantry/logs.py
gantry/sdk.py
gantry/sdkconfiguration.py
gantry/_hooks/__init__.py
gantry/_hooks/sdkhooks.py
gantry/_hooks/types.py
gantry/logger/__init__.py
gantry/logger/consumer.py
gantry/logger/eval_logger.py
gantry/logger/eval_reports.py
gantry/logger/langchain_callback.py
gantry/logger/log_location.py
gantry/logger/utils.py
gantry/models/__init__.py
gantry/models/components/__init__.py
gantry/models/components/createragevaluationrequest.py
gantry/models/components/criteriafeedback.py
gantry/models/components/criteriaresultcapture.py
gantry/models/components/criteriastats.py
gantry/models/components/criteriastatuscount.py
gantry/models/components/customstep.py
gantry/models/components/document.py
gantry/models/components/evalcriteria.py
gantry/models/components/evalstats.py
gantry/models/components/evaluationcriteriastatus.py
gantry/models/components/evaluationrecordstatus.py
gantry/models/components/evaluationrun.py
gantry/models/components/evaluationrunjobstatus.py
gantry/models/components/evaluationrunpreupload.py
gantry/models/components/evaluationrunpreuploadresponse.py
gantry/models/components/evaluationrunresponse.py
gantry/models/components/functionstep.py
gantry/models/components/getlogssummaryrequest.py
gantry/models/components/getragevaluationresultsresponse.py
gantry/models/components/getragevaluationresultsresponseresponse.py
gantry/models/components/llmevaluationcriteriatype.py
gantry/models/components/llmevaluationerrortype.py
gantry/models/components/llmstep.py
gantry/models/components/logerrorrequest.py
gantry/models/components/logerrorresponseresponse.py
gantry/models/components/logragrecordrequest.py
gantry/models/components/logragrecordresponse.py
gantry/models/components/logragrecordresponseresponse.py
gantry/models/components/message.py
gantry/models/components/organizationtier.py
gantry/models/components/orguser.py
gantry/models/components/passfailunsurerubricscalevalues.py
gantry_logger-0.0.2a7.dist-info/METADATA
gantry_logger-0.0.2a7.dist-info/WHEEL
gantry_logger-0.0.2a7.dist-info/top_level.txt
gantry_logger-0.0.2a7.dist-info/RECORD
