Metadata-Version: 2.1
Name: gantry-logger
Version: 0.0.2a7
Summary: Gantry Python Library
Author: Gantry Systems, Inc.
Author-email: oss@gantry.io
License: Apache Software License v2
Classifier: Development Status :: 4 - Beta
Classifier: Programming Language :: Python :: 3.8
Classifier: Programming Language :: Python :: 3.9
Classifier: Programming Language :: Python :: 3.10
Classifier: Programming Language :: Python :: 3.11
Classifier: License :: OSI Approved :: Apache Software License
Classifier: Operating System :: OS Independent
Requires-Python: >=3.8
Requires-Dist: pydantic
Requires-Dist: certifi >=2023.7.22
Requires-Dist: charset-normalizer >=3.2.0
Requires-Dist: dataclasses-json >=0.6.1
Requires-Dist: idna >=3.4
Requires-Dist: jsonpath-python >=1.0.6
Requires-Dist: marshmallow >=3.19.0
Requires-Dist: mypy-extensions >=1.0.0
Requires-Dist: packaging >=23.1
Requires-Dist: python-dateutil >=2.8.2
Requires-Dist: requests >=2.31.0
Requires-Dist: six >=1.16.0
Requires-Dist: typing-inspect >=0.9.0
Requires-Dist: typing-extensions >=4.7.1
Requires-Dist: urllib3 >=1.26.18
